losetup.py
setup.py
losetup.egg-info/PKG-INFO
losetup.egg-info/SOURCES.txt
losetup.egg-info/dependency_links.txt
losetup.egg-info/top_level.txt