Metadata-Version: 1.0
Name: losetup
Version: 2.0.7
Summary: Python API for "loop" Linux module
Home-page: UNKNOWN
Author: Sergey Kirillov
Author-email: serg@rainboo.com
License: UNKNOWN
Platform: UNKNOWN
